[
    {
        "name": "Great Value Organic Ground Ginger, 1.6 oz",
        "quantity": "Qty 1",
        "price": "$4.36",
        "date": "Jun 19, 2023 order"
    },
    {
        "name": "White Onions, Each",
        "quantity": "Qty 1",
        "price": "$0.82",
        "date": "Jun 19, 2023 order"
    },
    {
        "name": "Fresh Green Onions Bunch, Each",
        "quantity": "Qty 1",
        "price": "$0.88",
        "date": "Jun 19, 2023 order"
    },
    {
        "name": "Fresh Large Hass Avocado Bag, 3- 4 Count",
        "quantity": "Qty 1",
        "price": "$3.74",
        "date": "Jun 19, 2023 order"
    },
    {
        "name": "Fresh Cilantro, Bunch",
        "quantity": "Qty 1",
        "price": "$0.88",
        "date": "Jun 19, 2023 order"
    },
    {
        "name": "Fresh Roma Tomato, Each",
        "quantity": "Qty 3",
        "price": "$1.13",
        "date": "Jun 19, 2023 order"
    },
    {
        "name": "Bibigo Steamed Dumplings - Chicken and Vegetable, 6.6 oz (Frozen)",
        "quantity": "Qty 2",
        "price": "$7.04",
        "date": "Jun 19, 2023 order"
    },
    {
        "name": "Great Value Frozen Broccoli Florets, 12 oz Steamable Bag",
        "quantity": "Qty 2",
        "price": "$2.32",
        "date": "Jun 19, 2023 order"
    },
    {
        "name": "Great Value Finely Shredded Fiesta Blend Cheese, 32 oz",
        "quantity": "Qty 1",
        "price": "$7.48",
        "date": "Jun 19, 2023 order"
    },
    {
        "name": "Great Value Long Grain Enriched Rice, 5 lbs",
        "quantity": "Qty 2",
        "price": "$5.88",
        "date": "Jun 19, 2023 order"
    },
    {
        "name": "Great Value Bowties Pasta, 12 oz",
        "quantity": "Qty 2",
        "price": "$1.96",
        "date": "Jun 19, 2023 order"
    },
    {
        "name": "Mac's Original Crispy Fried Pork Skins, 5 oz Bag",
        "quantity": "Qty 1",
        "price": "$2.18",
        "date": "Jun 19, 2023 order"
    },
    {
        "name": "",
        "quantity": "",
        "price": "",
        "date": "Jun 19, 2023 order"
    },
    {
        "name": "",
        "quantity": "",
        "price": "",
        "date": "Jun 19, 2023 order"
    },
    {
        "name": "Navel Oranges, 4 lb Bag",
        "quantity": "Qty 1",
        "price": "$4.98",
        "date": "Jun 15, 2023 order"
    },
    {
        "name": "Post Honey Bunches of Oats with Almonds Breakfast Cereal, Family Size Cereal, 28 OZ Box",
        "quantity": "Qty 1",
        "price": "$5.98",
        "date": "Jun 15, 2023 order"
    },
    {
        "name": "Great Value Lactose Free 2% Reduced Fat Milk, Half Gallon, 64 fl oz",
        "quantity": "Qty 4",
        "price": "$13.52",
        "date": "Jun 15, 2023 order"
    },
    {
        "name": "Great Value California Style Vegetable Mix, 12 oz (Frozen)",
        "quantity": "Qty 2",
        "price": "$2.54",
        "date": "Jun 15, 2023 order"
    },
    {
        "name": "Cacique Ranchero Fresh Queso Fresco Cheese, 10 oz",
        "quantity": "Qty 1",
        "price": "$3.30",
        "date": "Jun 15, 2023 order"
    },
    {
        "name": "Equate Upset Stomach Relief Bismuth Liquid, Regular Strength, 16 fl oz",
        "quantity": "Qty 1",
        "price": "$3.56",
        "date": "Jun 15, 2023 order"
    },
    {
        "name": "White Onions, Each",
        "quantity": "Qty 1",
        "price": "$0.89",
        "date": "Jun 12, 2023 order"
    },
    {
        "name": "Fresh Roma Tomato, Each",
        "quantity": "Qty 3",
        "price": "$1.71",
        "date": "Jun 12, 2023 order"
    },
    {
        "name": "Fresh Cilantro, Bunch",
        "quantity": "Qty 1",
        "price": "$0.88",
        "date": "Jun 12, 2023 order"
    },
    {
        "name": "Lay's Potato Chips, Limon Flavor, 7.75 oz Bag",
        "quantity": "Qty 1",
        "price": "$2.76",
        "date": "Jun 12, 2023 order"
    },
    {
        "name": "Takis Fuego Rolls 9.9 oz Bag, Hot Chili Pepper & Lime Flavored Spicy Tortilla Chips",
        "quantity": "Qty 1",
        "price": "$3.78",
        "date": "Jun 12, 2023 order"
    },
    {
        "name": "HERDEZ Salsa Verde Mexican Salsa, Tortilla Chip Dip, Mild, 16oz Jar",
        "quantity": "Qty 2",
        "price": "$5.08",
        "date": "Jun 12, 2023 order"
    },
    {
        "name": "Great Value All Natural Sour Cream, 8 oz Tub",
        "quantity": "Qty 1",
        "price": "$1.16",
        "date": "Jun 12, 2023 order"
    },
    {
        "name": "La Banderita White Corn Tortillas, 66.3 oz",
        "quantity": "Qty 1",
        "price": "$3.64",
        "date": "Jun 12, 2023 order"
    },
    {
        "name": "Tortillaland Ready to Cook Soft Taco Size Flour Tortillas, 18 Count",
        "quantity": "Qty 1",
        "price": "$4.47",
        "date": "Jun 12, 2023 order"
    },
    {
        "name": "Great Value 100% Whole Wheat Bread Loaf, 24 oz",
        "quantity": "Qty 1",
        "price": "$2.48",
        "date": "Jun 12, 2023 order"
    },
    {
        "name": "Limes, Each",
        "quantity": "Qty 2",
        "price": "$0.76",
        "date": "Jun 12, 2023 order"
    },
    {
        "name": "Fresh Idaho Potatoes, 5 lb Bag",
        "quantity": "Qty 1",
        "price": "$3.67",
        "date": "Jun 12, 2023 order"
    },
    {
        "name": "Freshness Guaranteed Mild Guacamole Mini Cups, 12 oz, 6 Count",
        "quantity": "Qty 1",
        "price": "$4.18",
        "date": "Jun 12, 2023 order"
    },
    {
        "name": "RITZ Original Crackers, 13.7 oz",
        "quantity": "Qty 1",
        "price": "$3.88",
        "date": "Jun 12, 2023 order"
    },
    {
        "name": "Upgrade 2 in 1 Bath and Shampoo Brush, Silicone Body Scrubber for Use in Shower, Exfoliating Body Brush, Scalp Massager/Brush (Blue)",
        "quantity": "Qty 1",
        "price": "$9.45",
        "date": "Jun 12, 2023 order"
    },
    {
        "name": "Navel Oranges, 4 lb Bag",
        "quantity": "Qty 1",
        "price": "$4.98",
        "date": "Jun 05, 2023 order"
    },
    {
        "name": "Freshness Guaranteed Gala Apples, 3 lb Bag",
        "quantity": "Qty 1",
        "price": "$4.24",
        "date": "Jun 05, 2023 order"
    },
    {
        "name": "Great Value California Style Vegetable Mix, 12 oz (Frozen)",
        "quantity": "Qty 2",
        "price": "$2.54",
        "date": "Jun 05, 2023 order"
    },
    {
        "name": "Great Value Frozen Broccoli Florets, 12 oz Steamable Bag",
        "quantity": "Qty 4",
        "price": "$4.64",
        "date": "Jun 05, 2023 order"
    },
    {
        "name": "Great Value Lactose Free 2% Reduced Fat Milk, Half Gallon, 64 fl oz",
        "quantity": "Qty 3",
        "price": "$10.14",
        "date": "Jun 05, 2023 order"
    },
    {
        "name": "Great Value Minced Garlic in Water, 8 oz",
        "quantity": "Qty 1",
        "price": "$2.16",
        "date": "Jun 05, 2023 order"
    },
    {
        "name": "Great Value Large White Eggs, 60 Count",
        "quantity": "Qty 1",
        "price": "$7.66",
        "date": "Jun 05, 2023 order"
    },
    {
        "name": "Great Value Whole Grain Quick rolled Oats",
        "quantity": "Qty 1",
        "price": "$3.98",
        "date": "Jun 01, 2023 order"
    },
    {
        "name": "Post Honey Bunches of Oats with Almonds Breakfast Cereal, Family Size Cereal, 28 OZ Box",
        "quantity": "Qty 2",
        "price": "$11.96",
        "date": "Jun 01, 2023 order"
    },
    {
        "name": "HERDEZ Salsa Verde Mexican Salsa, Tortilla Chip Dip, Mild, 16oz Jar",
        "quantity": "Qty 1",
        "price": "$2.54",
        "date": "Jun 01, 2023 order"
    },
    {
        "name": "Great Value Lactose Free 2% Reduced Fat Milk, Half Gallon, 64 fl oz",
        "quantity": "Qty 2",
        "price": "$6.76",
        "date": "Jun 01, 2023 order"
    },
    {
        "name": "Mainstays 6 inch diameter x 5.6 inch high White Resin Self-watering Planter",
        "quantity": "Qty 1",
        "price": "$1.98",
        "date": "Jun 01, 2023 order"
    },
    {
        "name": "Great Value 100% Whole Wheat Bread Loaf, 24 oz",
        "quantity": "Qty 1",
        "price": "$2.48",
        "date": "Jun 01, 2023 order"
    },
    {
        "name": "Great Value Kettle Cooked Jalapeno Flavored Potato Chips, 8 oz",
        "quantity": "Qty 2",
        "price": "$3.96",
        "date": "Jun 01, 2023 order"
    },
    {
        "name": "Great Value Lactose Free 2% Reduced Fat Milk, Half Gallon, 64 fl oz",
        "quantity": "Qty 1",
        "price": "$3.38",
        "date": "Jun 01, 2023 order"
    },
    {
        "name": "Progresso, Italian Style Bread Crumbs, 15 oz.",
        "quantity": "Qty 1",
        "price": "$2.08",
        "date": "May 27, 2023 order"
    },
    {
        "name": "Navel Oranges, 4 lb Bag",
        "quantity": "Qty 1",
        "price": "$4.98",
        "date": "May 27, 2023 order"
    },
    {
        "name": "Fresh Roma Tomato, Each",
        "quantity": "Qty 3",
        "price": "$0.86",
        "date": "May 27, 2023 order"
    },
    {
        "name": "Spring Valley Vitamin C with Rose Hips Tablets Dietary Supplement, 1,000 mg, 250 Count",
        "quantity": "Qty 1",
        "price": "$9.88",
        "date": "May 27, 2023 order"
    },
    {
        "name": "Equate Daily Fiber, 100% Psyllium Husk Dietary Supplement Capsules, 300 Count",
        "quantity": "Qty 1",
        "price": "$10.98",
        "date": "May 27, 2023 order"
    },
    {
        "name": "Breyers Frozen Dairy Dessert Cookies & Cream Ice Cream Alternative, 48 oz",
        "quantity": "Qty 1",
        "price": "$4.97",
        "date": "May 27, 2023 order"
    },
    {
        "name": "Great Value Finely Shredded Fiesta Blend Cheese, 32 oz",
        "quantity": "Qty 1",
        "price": "$7.48",
        "date": "May 27, 2023 order"
    },
    {
        "name": "Great Value Long Grain Enriched Rice, 5 lbs",
        "quantity": "Qty 2",
        "price": "$5.88",
        "date": "May 27, 2023 order"
    },
    {
        "name": "Great Value Gv Chkn Brth 32",
        "quantity": "Qty 2",
        "price": "$2.74",
        "date": "May 27, 2023 order"
    },
    {
        "name": "Fresh Green Onions Bunch, Each",
        "quantity": "Qty 1",
        "price": "$0.88",
        "date": "May 27, 2023 order"
    },
    {
        "name": "McCormick Garlic Powder, 3.12 oz",
        "quantity": "Qty 1",
        "price": "$4.23",
        "date": "May 27, 2023 order"
    },
    {
        "name": "",
        "quantity": "",
        "price": "",
        "date": "May 27, 2023 order"
    },
    {
        "name": "White Onions, Each",
        "quantity": "Qty 1",
        "price": "$0.72",
        "date": "May 24, 2023 order"
    },
    {
        "name": "Quaker Life Multigrain Cereal Original, Family Size, 22.3 oz",
        "quantity": "Qty 1",
        "price": "$4.78",
        "date": "May 24, 2023 order"
    },
    {
        "name": "OREO Chocolate Sandwich Cookies, Family Size, 18.12 oz",
        "quantity": "Qty 1",
        "price": "$4.58",
        "date": "May 24, 2023 order"
    },
    {
        "name": "Great Value Cream Cheese, 8 oz, 2 Count",
        "quantity": "Qty 1",
        "price": "$3.18",
        "date": "May 24, 2023 order"
    },
    {
        "name": "Great Value Heavy Whipping Cream, 32 oz",
        "quantity": "Qty 1",
        "price": "$4.98",
        "date": "May 24, 2023 order"
    },
    {
        "name": "Great Value Lactose Free 2% Reduced Fat Milk, Half Gallon, 64 fl oz",
        "quantity": "Qty 4",
        "price": "$13.52",
        "date": "May 24, 2023 order"
    },
    {
        "name": "Great Value Large White Eggs, 60 Count",
        "quantity": "Qty 1",
        "price": "$8.24",
        "date": "May 24, 2023 order"
    },
    {
        "name": "Great Value Gv Chkn Brth 32",
        "quantity": "Qty 1",
        "price": "$1.33",
        "date": "May 24, 2023 order"
    },
    {
        "name": "Great Value Onion Powder, 3.25 oz",
        "quantity": "Qty 1",
        "price": "$1.12",
        "date": "May 24, 2023 order"
    },
    {
        "name": "",
        "quantity": "",
        "price": "",
        "date": "May 24, 2023 order"
    },
    {
        "name": "Marketside Organic Bananas, Bunch",
        "quantity": "Qty 1",
        "price": "$1.84",
        "date": "May 17, 2023 order"
    },
    {
        "name": "Navel Oranges, 4 lb Bag",
        "quantity": "Qty 1",
        "price": "$4.98",
        "date": "May 17, 2023 order"
    },
    {
        "name": "Organic Marketside Fresh Baby Peeled Carrots, 1 lb Bag",
        "quantity": "Qty 1",
        "price": "$1.56",
        "date": "May 17, 2023 order"
    },
    {
        "name": "Outshine Mango Frozen Fruit Bars, 6 Count",
        "quantity": "Qty 1",
        "price": "$3.98",
        "date": "May 17, 2023 order"
    },
    {
        "name": "Outshine Watermelon Frozen Fruit Bars, 6 Count",
        "quantity": "Qty 1",
        "price": "$3.98",
        "date": "May 17, 2023 order"
    },
    {
        "name": "Freshness Guaranteed Mild Guacamole Mini Cups, 12 oz, 6 Count",
        "quantity": "Qty 1",
        "price": "$4.18",
        "date": "May 17, 2023 order"
    },
    {
        "name": "Great Value Lactose Free 2% Reduced Fat Milk, Half Gallon, 64 fl oz",
        "quantity": "Qty 3",
        "price": "$10.14",
        "date": "May 17, 2023 order"
    },
    {
        "name": "Great Value 100% Whole Wheat Bread Loaf, 24 oz",
        "quantity": "Qty 1",
        "price": "$2.48",
        "date": "May 17, 2023 order"
    },
    {
        "name": "Nissin Bowl Noodles Hot & Spicy with Shrimp Ramen Noodle Soup, 3.32 Oz",
        "quantity": "Qty 2",
        "price": "$2.84",
        "date": "May 17, 2023 order"
    },
    {
        "name": "Freshness Guaranteed Gala Apples, 3 lb Bag",
        "quantity": "Qty 1",
        "price": "$4.24",
        "date": "May 17, 2023 order"
    },
    {
        "name": "Orville Redenbacher's Ultimate Butter Microwave Popcorn, 3.29 Oz, 12 Ct",
        "quantity": "Qty 1",
        "price": "$6.36",
        "date": "May 12, 2023 order"
    },
    {
        "name": "Great Value Large White Eggs, 60 Count",
        "quantity": "Qty 1",
        "price": "$8.24",
        "date": "May 12, 2023 order"
    },
    {
        "name": "Post Honey Bunches of Oats with Almonds Breakfast Cereal, Family Size Cereal, 28 OZ Box",
        "quantity": "Qty 1",
        "price": "$5.98",
        "date": "May 12, 2023 order"
    },
    {
        "name": "POWERADE Electrolyte Enhanced Fruit Punch Sport Drink, 20 fl oz, 8 Count Bottles",
        "quantity": "Qty 1",
        "price": "$5.78",
        "date": "May 12, 2023 order"
    },
    {
        "name": "",
        "quantity": "",
        "price": "",
        "date": "May 12, 2023 order"
    }
]